CHANGES
COPYING
INSTALL
MANIFEST.in
README
python_compat.h
setup.cfg
setup.py
textseg.c
textseg_Consts.c
pytextseg.egg-info/PKG-INFO
pytextseg.egg-info/SOURCES.txt
pytextseg.egg-info/dependency_links.txt
pytextseg.egg-info/top_level.txt
sombok/ARTISTIC
sombok/COPYING
sombok/ChangeLog
sombok/ChangeLog.REL1
sombok/README
sombok/README.ja_JP
sombok/UNICODE
sombok/VERSION
sombok/include/sombok.h.in
sombok/include/sombok_constants.h
sombok/lib/5.1.0.c
sombok/lib/5.2.0.c
sombok/lib/6.0.0.c
sombok/lib/6.1.0.c
sombok/lib/break.c
sombok/lib/charprop.c
sombok/lib/gcstring.c
sombok/lib/linebreak.c
sombok/lib/southeastasian.c
sombok/lib/utf8.c
sombok/lib/utils.c
source/back.rst
source/changes.rst
source/conf.py
source/custom.rst
source/doc.rst
source/glossary.rst
source/index.rst
source/install.rst
source/notes.rst
test-data/GraphemeBreakTest.txt
test-data/LineBreakTest.txt
test-data/amitagyong.in
test-data/amitagyong.out
test-data/ar.in
test-data/ar.out
test-data/ecclesiazusae.CharactersMax.out
test-data/ecclesiazusae.ColumnsMax.out
test-data/ecclesiazusae.ColumnsMin.out
test-data/ecclesiazusae.in
test-data/ecclesiazusae.out
test-data/el.in
test-data/el.out
test-data/flowedsp.in
test-data/flowedsp.out
test-data/fr.ea.out
test-data/fr.fixed.out
test-data/fr.flowed.out
test-data/fr.format.out
test-data/fr.in
test-data/fr.newline.out
test-data/fr.out
test-data/fr.plain.out
test-data/fr.wrap.out
test-data/he.in
test-data/he.out
test-data/ja-a.in
test-data/ja-a.out
test-data/ja-k.in
test-data/ja-k.ns.out
test-data/ja-k.out
test-data/ja.fixed.out
test-data/ja.flowed.out
test-data/ja.format.out
test-data/ja.in
test-data/ja.out
test-data/ja.plain.out
test-data/ja.wrap.out
test-data/ko.al.out
test-data/ko.in
test-data/ko.newline.out
test-data/ko.out
test-data/quotes.fixed.out
test-data/quotes.flowed.out
test-data/quotes.in
test-data/quotes.norm.in
test-data/quotes.plain.out
test-data/ru.in
test-data/ru.out
test-data/sa.in
test-data/sa.out
test-data/th.al.out
test-data/th.in
test-data/th.out
test-data/titin.bz
test-data/uri.break.http.out
test-data/uri.break.out
test-data/uri.in
test-data/uri.nonbreak.out
